{
 "charts": [],
 "content": "[{\"id\":\"CEZNmuFvIS\",\"type\":\"header\",\"data\":{\"text\":\"<span class=\\\"h4\\\">Service Pro</span>\",\"col\":12}},{\"id\":\"PJv00ZAXu4\",\"type\":\"shortcut\",\"data\":{\"shortcut_name\":\"Receipt Note\",\"col\":3}},{\"id\":\"d1X_o5nILw\",\"type\":\"shortcut\",\"data\":{\"shortcut_name\":\"Estimation\",\"col\":3}},{\"id\":\"yt-2LFOOCO\",\"type\":\"shortcut\",\"data\":{\"shortcut_name\":\"Inspection\",\"col\":3}},{\"id\":\"uIBFXxf7E4\",\"type\":\"shortcut\",\"data\":{\"shortcut_name\":\"Production\",\"col\":3}},{\"id\":\"UjN6Q55QgN\",\"type\":\"shortcut\",\"data\":{\"shortcut_name\":\"Material Request\",\"col\":3}},{\"id\":\"eXHM803PHx\",\"type\":\"shortcut\",\"data\":{\"shortcut_name\":\"Sales Invoice\",\"col\":3}},{\"id\":\"koTARpeBRL\",\"type\":\"spacer\",\"data\":{\"col\":12}},{\"id\":\"IZH2WKrbor\",\"type\":\"card\",\"data\":{\"card_name\":\"Showroom Masters\",\"col\":4}},{\"id\":\"W8irLy14s7\",\"type\":\"card\",\"data\":{\"card_name\":\"Site Service Masters\",\"col\":4}},{\"id\":\"OkNdx7Fgfd\",\"type\":\"card\",\"data\":{\"card_name\":\"Workshop Masters\",\"col\":4}},{\"id\":\"Du-RosDfCy\",\"type\":\"card\",\"data\":{\"card_name\":\"Reports\",\"col\":4}},{\"id\":\"O_6I5KFHHd\",\"type\":\"card\",\"data\":{\"card_name\":\"Custom Master\",\"col\":4}}]",
 "creation": "2023-04-22 11:28:23.611529",
 "custom_blocks": [],
 "docstatus": 0,
 "doctype": "Workspace",
 "for_user": "",
 "hide_custom": 0,
 "icon": "organization",
 "idx": 0,
 "is_hidden": 0,
 "label": "Service Pro",
 "links": [
  {
   "hidden": 0,
   "is_query_report": 0,
   "label": "Customer",
   "link_count": 0,
   "link_to": "Customer",
   "link_type": "DocType",
   "onboard": 0,
   "type": "Link"
  },
  {
   "hidden": 0,
   "is_query_report": 0,
   "label": "Supplier",
   "link_count": 0,
   "link_to": "Supplier",
   "link_type": "DocType",
   "onboard": 0,
   "type": "Link"
  },
  {
   "hidden": 0,
   "is_query_report": 0,
   "label": "Stock Entry",
   "link_count": 0,
   "link_to": "Stock Entry",
   "link_type": "DocType",
   "onboard": 0,
   "type": "Link"
  },
  {
   "hidden": 0,
   "is_query_report": 0,
   "label": "Petty Cash Request",
   "link_count": 0,
   "link_to": "Petty Cash Request",
   "link_type": "DocType",
   "onboard": 0,
   "type": "Link"
  },
  {
   "hidden": 0,
   "is_query_report": 0,
   "label": "Payment Schedule",
   "link_count": 0,
   "link_to": "Payment Schedule",
   "link_type": "DocType",
   "onboard": 0,
   "type": "Link"
  },
  {
   "hidden": 0,
   "is_query_report": 0,
   "label": "Agent Payment Request",
   "link_count": 0,
   "link_to": "Agent Payment Request",
   "link_type": "DocType",
   "onboard": 0,
   "type": "Link"
  },
  {
   "hidden": 0,
   "is_query_report": 0,
   "label": "Related Party Entry",
   "link_count": 0,
   "link_to": "Related Party Entry",
   "link_type": "DocType",
   "onboard": 0,
   "type": "Link"
  },
  {
   "hidden": 0,
   "is_query_report": 0,
   "label": "Reports",
   "link_count": 6,
   "link_type": "DocType",
   "onboard": 0,
   "type": "Card Break"
  },
  {
   "hidden": 0,
   "is_query_report": 0,
   "label": "Stock Balance",
   "link_count": 0,
   "link_to": "Stock Balance",
   "link_type": "Report",
   "onboard": 0,
   "type": "Link"
  },
  {
   "hidden": 0,
   "is_query_report": 0,
   "label": "Stock Ledger",
   "link_count": 0,
   "link_to": "Stock Ledger",
   "link_type": "Report",
   "onboard": 0,
   "type": "Link"
  },
  {
   "hidden": 0,
   "is_query_report": 0,
   "label": "Stock List Report",
   "link_count": 0,
   "link_to": "Stock List Report",
   "link_type": "Report",
   "onboard": 0,
   "type": "Link"
  },
  {
   "hidden": 0,
   "is_query_report": 0,
   "label": "Statement of Account",
   "link_count": 0,
   "link_to": "Statement of Account",
   "link_type": "Report",
   "onboard": 0,
   "type": "Link"
  },
  {
   "hidden": 0,
   "is_query_report": 0,
   "label": "Simple EOD",
   "link_count": 0,
   "link_to": "Simple EOD",
   "link_type": "Report",
   "onboard": 0,
   "type": "Link"
  },
  {
   "hidden": 0,
   "is_query_report": 0,
   "label": "PC Report",
   "link_count": 0,
   "link_to": "PC Report",
   "link_type": "Report",
   "onboard": 0,
   "type": "Link"
  },
  {
   "hidden": 0,
   "is_query_report": 0,
   "label": "Custom Master",
   "link_count": 5,
   "link_type": "DocType",
   "onboard": 0,
   "type": "Card Break"
  },
  {
   "hidden": 0,
   "is_query_report": 0,
   "label": "Petty Cash Request",
   "link_count": 0,
   "link_to": "Petty Cash Request",
   "link_type": "DocType",
   "onboard": 0,
   "type": "Link"
  },
  {
   "hidden": 0,
   "is_query_report": 0,
   "label": "Agent Payment Request",
   "link_count": 0,
   "link_to": "Agent Payment Request",
   "link_type": "DocType",
   "onboard": 0,
   "type": "Link"
  },
  {
   "hidden": 0,
   "is_query_report": 0,
   "label": "Related Party Entry",
   "link_count": 0,
   "link_to": "Related Party Entry",
   "link_type": "DocType",
   "onboard": 0,
   "type": "Link"
  },
  {
   "hidden": 0,
   "is_query_report": 0,
   "label": "Sales Partner Payments",
   "link_count": 0,
   "link_to": "Sales Partner Payments",
   "link_type": "DocType",
   "onboard": 0,
   "type": "Link"
  },
  {
   "hidden": 0,
   "is_query_report": 0,
   "label": "Inter Company Stock Transfer",
   "link_count": 0,
   "link_to": "Inter Company Stock Transfer",
   "link_type": "DocType",
   "onboard": 0,
   "type": "Link"
  },
  {
   "hidden": 0,
   "is_query_report": 0,
   "label": "Workshop Masters",
   "link_count": 12,
   "link_type": "DocType",
   "onboard": 0,
   "type": "Card Break"
  },
  {
   "hidden": 0,
   "is_query_report": 0,
   "label": "Service Receipt Note",
   "link_count": 0,
   "link_to": "Service Receipt Note",
   "link_type": "DocType",
   "onboard": 0,
   "type": "Link"
  },
  {
   "hidden": 0,
   "is_query_report": 0,
   "label": "Inspection",
   "link_count": 0,
   "link_to": "Inspection",
   "link_type": "DocType",
   "onboard": 0,
   "type": "Link"
  },
  {
   "hidden": 0,
   "is_query_report": 0,
   "label": "Estimation",
   "link_count": 0,
   "link_to": "Estimation",
   "link_type": "DocType",
   "onboard": 0,
   "type": "Link"
  },
  {
   "hidden": 0,
   "is_query_report": 0,
   "label": "Production",
   "link_count": 0,
   "link_to": "Production",
   "link_type": "DocType",
   "onboard": 0,
   "type": "Link"
  },
  {
   "hidden": 0,
   "is_query_report": 0,
   "label": "Quotation",
   "link_count": 0,
   "link_to": "Quotation",
   "link_type": "DocType",
   "onboard": 0,
   "type": "Link"
  },
  {
   "hidden": 0,
   "is_query_report": 0,
   "label": "Sales Order",
   "link_count": 0,
   "link_to": "Sales Order",
   "link_type": "DocType",
   "onboard": 0,
   "type": "Link"
  },
  {
   "hidden": 0,
   "is_query_report": 0,
   "label": "Sales Invoice",
   "link_count": 0,
   "link_to": "Sales Invoice",
   "link_type": "DocType",
   "onboard": 0,
   "type": "Link"
  },
  {
   "hidden": 0,
   "is_query_report": 0,
   "label": "Delivery Note",
   "link_count": 0,
   "link_to": "Delivery Note",
   "link_type": "DocType",
   "onboard": 0,
   "type": "Link"
  },
  {
   "hidden": 0,
   "is_query_report": 0,
   "label": "Job Completion Report",
   "link_count": 0,
   "link_to": "Job Completion Report",
   "link_type": "DocType",
   "onboard": 0,
   "type": "Link"
  },
  {
   "hidden": 0,
   "is_query_report": 0,
   "label": "Customer",
   "link_count": 0,
   "link_to": "Customer",
   "link_type": "DocType",
   "onboard": 0,
   "type": "Link"
  },
  {
   "hidden": 0,
   "is_query_report": 0,
   "label": "Supplier",
   "link_count": 0,
   "link_to": "Supplier",
   "link_type": "DocType",
   "onboard": 0,
   "type": "Link"
  },
  {
   "hidden": 0,
   "is_query_report": 0,
   "label": "Stock Entry",
   "link_count": 0,
   "link_to": "Stock Entry",
   "link_type": "DocType",
   "onboard": 0,
   "type": "Link"
  },
  {
   "hidden": 0,
   "is_query_report": 0,
   "label": "Showroom Masters",
   "link_count": 8,
   "link_type": "DocType",
   "onboard": 0,
   "type": "Card Break"
  },
  {
   "hidden": 0,
   "is_query_report": 0,
   "label": "Production",
   "link_count": 0,
   "link_to": "Production",
   "link_type": "DocType",
   "onboard": 0,
   "type": "Link"
  },
  {
   "hidden": 0,
   "is_query_report": 0,
   "label": "Quotation",
   "link_count": 0,
   "link_to": "Quotation",
   "link_type": "DocType",
   "onboard": 0,
   "type": "Link"
  },
  {
   "hidden": 0,
   "is_query_report": 0,
   "label": "Sales Order",
   "link_count": 0,
   "link_to": "Sales Order",
   "link_type": "DocType",
   "onboard": 0,
   "type": "Link"
  },
  {
   "hidden": 0,
   "is_query_report": 0,
   "label": "Sales Invoice",
   "link_count": 0,
   "link_to": "Sales Invoice",
   "link_type": "DocType",
   "onboard": 0,
   "type": "Link"
  },
  {
   "hidden": 0,
   "is_query_report": 0,
   "label": "Delivery Note",
   "link_count": 0,
   "link_to": "Delivery Note",
   "link_type": "DocType",
   "onboard": 0,
   "type": "Link"
  },
  {
   "hidden": 0,
   "is_query_report": 0,
   "label": "Sales Person",
   "link_count": 0,
   "link_to": "Sales Person",
   "link_type": "DocType",
   "onboard": 0,
   "type": "Link"
  },
  {
   "hidden": 0,
   "is_query_report": 0,
   "label": "Customer",
   "link_count": 0,
   "link_to": "Customer",
   "link_type": "DocType",
   "onboard": 0,
   "type": "Link"
  },
  {
   "hidden": 0,
   "is_query_report": 0,
   "label": "Supplier",
   "link_count": 0,
   "link_to": "Supplier",
   "link_type": "DocType",
   "onboard": 0,
   "type": "Link"
  },
  {
   "hidden": 0,
   "is_query_report": 0,
   "label": "Site Service Masters",
   "link_count": 9,
   "link_type": "DocType",
   "onboard": 0,
   "type": "Card Break"
  },
  {
   "hidden": 0,
   "is_query_report": 0,
   "label": "Site Visit Report",
   "link_count": 0,
   "link_to": "Site Visit Report",
   "link_type": "DocType",
   "onboard": 0,
   "type": "Link"
  },
  {
   "hidden": 0,
   "is_query_report": 0,
   "label": "Site Job Report",
   "link_count": 0,
   "link_to": "Site Job Report",
   "link_type": "DocType",
   "onboard": 0,
   "type": "Link"
  },
  {
   "hidden": 0,
   "is_query_report": 0,
   "label": "Job Completion Report",
   "link_count": 0,
   "link_to": "Job Completion Report",
   "link_type": "DocType",
   "onboard": 0,
   "type": "Link"
  },
  {
   "hidden": 0,
   "is_query_report": 0,
   "label": "Production",
   "link_count": 0,
   "link_to": "Production",
   "link_type": "DocType",
   "onboard": 0,
   "type": "Link"
  },
  {
   "hidden": 0,
   "is_query_report": 0,
   "label": "Quotation",
   "link_count": 0,
   "link_to": "Quotation",
   "link_type": "DocType",
   "onboard": 0,
   "type": "Link"
  },
  {
   "hidden": 0,
   "is_query_report": 0,
   "label": "Sales Order",
   "link_count": 0,
   "link_to": "Sales Order",
   "link_type": "DocType",
   "onboard": 0,
   "type": "Link"
  },
  {
   "hidden": 0,
   "is_query_report": 0,
   "label": "Sales Invoice",
   "link_count": 0,
   "link_to": "Sales Invoice",
   "link_type": "DocType",
   "onboard": 0,
   "type": "Link"
  },
  {
   "hidden": 0,
   "is_query_report": 0,
   "label": "Customer",
   "link_count": 0,
   "link_to": "Customer",
   "link_type": "DocType",
   "onboard": 0,
   "type": "Link"
  },
  {
   "hidden": 0,
   "is_query_report": 0,
   "label": "Supplier",
   "link_count": 0,
   "link_to": "Supplier",
   "link_type": "DocType",
   "onboard": 0,
   "type": "Link"
  }
 ],
 "modified": "2024-09-01 12:02:33.185249",
 "modified_by": "Administrator",
 "module": "Service Pro",
 "name": "Service Pro",
 "number_cards": [],
 "owner": "Administrator",
 "parent_page": "",
 "public": 1,
 "quick_lists": [],
 "roles": [],
 "sequence_id": 33.0,
 "shortcuts": [
  {
   "color": "Grey",
   "doc_view": "List",
   "label": "Receipt Note",
   "link_to": "Service Receipt Note",
   "type": "DocType"
  },
  {
   "color": "Grey",
   "doc_view": "List",
   "label": "Estimation",
   "link_to": "Estimation",
   "type": "DocType"
  },
  {
   "color": "Grey",
   "doc_view": "List",
   "label": "Inspection",
   "link_to": "Inspection",
   "type": "DocType"
  },
  {
   "color": "Grey",
   "doc_view": "List",
   "label": "Production",
   "link_to": "Production",
   "type": "DocType"
  },
  {
   "color": "Grey",
   "doc_view": "List",
   "label": "Material Request",
   "link_to": "Material Request",
   "type": "DocType"
  },
  {
   "color": "Grey",
   "doc_view": "List",
   "label": "Sales Invoice",
   "link_to": "Sales Invoice",
   "type": "DocType"
  }
 ],
 "title": "Service Pro"
}